README
setup.py
reutil/__init__.py
reutil.egg-info/PKG-INFO
reutil.egg-info/SOURCES.txt
reutil.egg-info/dependency_links.txt
reutil.egg-info/top_level.txt