Metadata-Version: 1.0
Name: reutil
Version: 0.1.0
Summary: Utilities for working with multiple regular expressions
Home-page: https://github.com/gregoryv/reutil
Author: Gregory Vincic
Author-email: g@7de.se
License: GPLv3
Platform: UNKNOWN
